Metadata-Version: 2.1
Name: terminalbreaker
Version: 0.1.6
Summary: BREAK THE TERMINAL! Create panels, forms, dialogs and buttons into your Python CLI app!
Home-page: https://github.com/Ellicode/terminalbreaker/blob/main/README.md
Author: Ellicode
Author-email: ellicode22@gmail.com
License: MIT
Keywords: example project
Platform: UNKNOWN
License-File: LICENSE
